beren/VERSION
beren/__init__.py
beren/orthanc.py
beren/endpoints/__init__.py
beren/endpoints/instances.py
beren/endpoints/misc.py
beren/endpoints/modalities.py
beren/endpoints/patients.py
beren/endpoints/queries.py
beren/endpoints/series.py
beren/endpoints/studies.py
beren-0.7.1.dist-info/LICENSE
beren-0.7.1.dist-info/METADATA
beren-0.7.1.dist-info/WHEEL
beren-0.7.1.dist-info/top_level.txt
beren-0.7.1.dist-info/RECORD
