Metadata-Version: 2.1
Name: beren
Version: 0.7.1
Summary: REST client for Orthanc DICOM servers
Home-page: https://github.com/teffalump/beren
Author: teffalump
Author-email: chris@teffalump.com
License: UNKNOWN
Platform: UNKNOWN
Classifier: Development Status :: 4 - Beta
Classifier: Programming Language :: Python :: 3
Classifier: Programming Language :: Python :: 3 :: Only
Classifier: Intended Audience :: Developers
Classifier: License :: OSI Approved :: GNU General Public License v3 or later (GPLv3+)
Classifier: Operating System :: OS Independent
License-File: LICENSE
Requires-Dist: apiron (==6.0.0)
